<?xml version="1.0" encoding="utf-8"?>
<cal_summary><meta><autoIncrement>1</autoIncrement></meta><data><row><id>1</id><MDse_2020_1>0.00037030705223282</MDse_2020_1><MD_2020>0.0052807714073373</MD_2020><ELse_2020_1>0.00014884760645111</ELse_2020_1><EL_2020>0.0083279757824508</EL_2020><MDse_2020_2>0.00094337163937425</MDse_2020_2><ELse_2020_2>0.00048868449787917</ELse_2020_2><MDse_2020_3>0.002992676081113</MDse_2020_3><ELse_2020_3>0.0028991447955487</ELse_2020_3><MDse_2020_4>0.0052807714073373</MDse_2020_4><ELse_2020_4>0.0047912988825718</ELse_2020_4><MDse_2025_1>9.0809692456886E-5</MDse_2025_1><MD_2025>0.0012801802141984</MD_2025><ELse_2025_1>3.6210145962056E-5</ELse_2025_1><EL_2025>0.002020202020202</EL_2025><MDse_2025_2>0.0002303145097161</MDse_2025_2><ELse_2025_2>0.00011895527268369</ELse_2025_2><MDse_2025_3>0.00072681061850835</MDse_2025_3><ELse_2025_3>0.00070367540346577</ELse_2025_3><MDse_2025_4>0.0012801802141984</MDse_2025_4><ELse_2025_4>0.0011613611980905</ELse_2025_4><RelAP_2020_1>0.070123666348878</RelAP_2020_1><LFse_2020_1>18.404636246197</LFse_2020_1><RelAP_2020_2>0.17864277140713</RelAP_2020_2><LFse_2020_2>35.383816154459</LFse_2020_2><RelAP_2020_3>0.56671191579225</RelAP_2020_3><LFse_2020_3>33.085608118293</LFse_2020_3><RelAP_2020_4>1</RelAP_2020_4><LFse_2020_4>41.09195707639</LFse_2020_4><LF_2020>17.953526133885</LF_2020><DifAD_2020>-6.2835556376084</DifAD_2020><DifADp_2020>-0.99867639386006</DifADp_2020><RelAP_2025_1>0.070935085115143</RelAP_2025_1><LFse_2025_1>18.460536546662</LFse_2025_1><RelAP_2025_2>0.17990788106369</RelAP_2025_2><LFse_2025_2>35.279410602508</LFse_2025_2><RelAP_2025_3>0.56774086214373</RelAP_2025_3><LFse_2025_3>33.06587615507</LFse_2025_3><RelAP_2025_4>1</RelAP_2025_4><LFse_2025_4>41.086309384367</LFse_2025_4><LF_2025>18.014390975198</LF_2025><DifAD_2025>-7.9042703592096</DifAD_2025><DifADp_2025>-0.99974448168777</DifADp_2025><SID>1</SID></row></data></cal_summary>
